IOTAssignmentUtilitiesdorachua/MyDateTimeUtilities.py
IOTAssignmentUtilitiesdorachua/MyJSONHelper.py
IOTAssignmentUtilitiesdorachua/MySQLManager.py
IOTAssignmentUtilitiesdorachua/OurCustomEncoder.py
IOTAssignmentUtilitiesdorachua/__init__.py
IOTAssignmentUtilitiesdorachua-0.0.18.dist-info/LICENSE
IOTAssignmentUtilitiesdorachua-0.0.18.dist-info/METADATA
IOTAssignmentUtilitiesdorachua-0.0.18.dist-info/WHEEL
IOTAssignmentUtilitiesdorachua-0.0.18.dist-info/top_level.txt
IOTAssignmentUtilitiesdorachua-0.0.18.dist-info/RECORD
